CHANGELOG.txt
LICENCE.txt
MANIFEST.in
README.txt
requirements.txt
setup.py
Xrommasfm.egg-info/PKG-INFO
Xrommasfm.egg-info/SOURCES.txt
Xrommasfm.egg-info/dependency_links.txt
Xrommasfm.egg-info/top_level.txt
room/GUI.py
room/Run.py
room/__init__.py
room/download.py